topsis/__init_.py
topsis/__main__.py
Topsis_naman_101916076-1.0.5.dist-info/LICENSE
Topsis_naman_101916076-1.0.5.dist-info/METADATA
Topsis_naman_101916076-1.0.5.dist-info/WHEEL
Topsis_naman_101916076-1.0.5.dist-info/entry_points.txt
Topsis_naman_101916076-1.0.5.dist-info/top_level.txt
Topsis_naman_101916076-1.0.5.dist-info/RECORD
