Metadata-Version: 2.1
Name: Topsis-naman-101916076
Version: 1.0.5
Summary: TOPSIS method for multiple-criteria decision making (MCDM).
Author: Naman Kalsotra
Author-email: Kalsotranaman@gmail.com
License: SELF
Platform: UNKNOWN
Classifier: Programming Language :: Python :: 3.9
License-File: LICENSE
Requires-Dist: pandas
